sphinx_gherkin/__init__.py
sphinx_gherkin/__main__.py
sphinx_gherkin/domain.py
sphinx_gherkin/gherkin.py
sphinx_gherkin/index.py
sphinx_gherkin/py.typed
sphinx_gherkin/sphinxapi.py
sphinx_gherkin/gherkin2rst/__init__.py
sphinx_gherkin/gherkin2rst/feature.rst_t
sphinx_gherkin/gherkin2rst/folder.rst_t
sphinx_gherkin/gherkin2rst/toc.rst_t
sphinx_gherkin/i18n/__init__.py
sphinx_gherkin/markup/__init__.py
sphinx_gherkin/markup/autodoc.py
sphinx_gherkin/viewcode/__init__.py
sphinx_gherkin/viewcode/html.py
sphinx_gherkin-0.1.dist-info/LICENSE
sphinx_gherkin-0.1.dist-info/METADATA
sphinx_gherkin-0.1.dist-info/WHEEL
sphinx_gherkin-0.1.dist-info/entry_points.txt
sphinx_gherkin-0.1.dist-info/top_level.txt
sphinx_gherkin-0.1.dist-info/RECORD
