Metadata-Version: 2.1
Name: sphinx-gherkin
Version: 0.1
Summary: A Sphinx extension for documenting Gherkin features.
Home-page: https://cblegare.gitlab.io/sphinx-gherkin
Author: Charles Bouchard-Légaré
Author-email: charlesbouchardlegare@gmail.com
License: BSD-2-Clause-Patent
Project-URL: Documentation, https://cblegare.gitlab.io/sphinx-gherkin
Project-URL: Source, https://gitlab.com/cblegare/sphinx-gherkin
Project-URL: Issue Tracker, https://gitlab.com/cblegare/sphinx-gherkin/-/issues
Keywords: gherkin sphinx
Platform: UNKNOWN
Classifier: Development Status :: 3 - Alpha
Classifier: Intended Audience :: Developers
Classifier: Intended Audience :: Information Technology
Classifier: Topic :: Documentation
Classifier: Topic :: Documentation :: Sphinx
Classifier: Framework :: Sphinx
Classifier: Framework :: Sphinx :: Extension
Classifier: License :: OSI Approved :: MIT License
Classifier: Programming Language :: Python :: 3.7
Classifier: Programming Language :: Python :: 3.8
Classifier: Programming Language :: Python :: 3.9
Classifier: Programming Language :: Python :: 3.10
Classifier: Operating System :: OS Independent
Classifier: Typing :: Typed
Requires-Python: >=3.7
License-File: LICENSE
Requires-Dist: sphinx (>=3)
Requires-Dist: docutils
Requires-Dist: gherkin-official
Requires-Dist: typing-extensions ; python_version < "3.8"
Requires-Dist: importlib-metadata ; python_version < "3.8"
Provides-Extra: all
Requires-Dist: nox ; extra == 'all'
Requires-Dist: sphinxcontrib-bibtex ; extra == 'all'
Requires-Dist: myst-parser ; extra == 'all'
Requires-Dist: sphinx-autodoc-typehints ; extra == 'all'
Requires-Dist: sphinxcontrib-programoutput ; extra == 'all'
Requires-Dist: sphinx-copybutton ; extra == 'all'
Requires-Dist: sphinx-tabs ; extra == 'all'
Requires-Dist: docutils (>=0.16) ; extra == 'all'
Requires-Dist: pydata-sphinx-theme ; extra == 'all'
Requires-Dist: sphinx-paramlinks ; extra == 'all'
Provides-Extra: docs
Requires-Dist: myst-parser ; extra == 'docs'
Requires-Dist: docutils (>=0.16) ; extra == 'docs'
Requires-Dist: sphinx-autodoc-typehints ; extra == 'docs'
Requires-Dist: sphinx-paramlinks ; extra == 'docs'
Requires-Dist: sphinx-copybutton ; extra == 'docs'
Requires-Dist: sphinxcontrib-bibtex ; extra == 'docs'
Requires-Dist: sphinxcontrib-programoutput ; extra == 'docs'
Requires-Dist: sphinx-tabs ; extra == 'docs'
Requires-Dist: pydata-sphinx-theme ; extra == 'docs'
Provides-Extra: markdown
Requires-Dist: myst-parser ; extra == 'markdown'
Requires-Dist: docutils (>=0.16) ; extra == 'markdown'
Provides-Extra: test
Requires-Dist: nox ; extra == 'test'
